{
  "step1": [
    {
      "id": "HTML",
      "text": "기본적인 태그를 사용하여 마크업을 할 수 있습니다.",
      "turn": 70
    },
    {
      "id": "SCSS",
      "text": "스타일명령을 사용하여 레이아웃과 디자인을 할 수 있습니다.",
      "turn": 60
    },
    {
      "id": "JS",
      "text": "바닐라문법을 사용하여 팀프로젝트에 참여한 경험이 있습니다.",
      "turn": 50
    },
    {
      "id": "Figma",
      "text": "피그마를 사용하여 컴포넌트와 간단한 애니메이션, 스토리보드를 제작할 수 있습니다.",
      "turn": 70
    }
  ],
  "step2": [
    {
      "id": "React",
      "text": "유지보수를 위해 컴포넌트를 분리하고 map을 활용해 반복문을 사용할 수 있습니다.",
      "turn": 50
    },
    {
      "id": "jQuery",
      "text": "jQuery를 사용해 DOM조작과 이벤트를 처리한 경험이 있습니다.",
      "turn": 40
    },
    {
      "id": "Mongo",
      "text": "데이터 구조를 이해하고 기본적인 데이터 관리 경험이 있습니다.",
      "turn": 30
    },
    {
      "id": "Ps",
      "text": "툴을 활용하여 이미지를 편집하고 일러스트를 만들 수 있습니다.",
      "turn": 90
    }
  ],
  "step3": [
    {
      "id": "Git",
      "text": "로컬 환경에서 코드의 변경 이력을 기록하고 관리한 경험이 있습니다.",
      "turn": 30
    },
    {
      "id": "GitHub",
      "text": "깃허브를 활용하여 팀/개인 프로젝트를 관리 한 경험이 있습니다.",
      "turn": 50
    },
    {
      "id": "Vercel",
      "text": "프로젝트를 배포하고 관리한 경험이 있습니다.",
      "turn": 30
    },
    {
      "id": "Ai",
      "text": "디자인 툴을 활용하여 일러스트를 만들고 편집할 수 있습니다.",
      "turn": 90
    }
  ]
}